baghchal/__init__.py
baghchal/engine.py
baghchal/env.py
baghchal/lookup_table.py
baghchal/images/bagh.png
baghchal/images/board.png
baghchal/images/goat.png
baghchal-1.0.1.dist-info/LICENSE.txt
baghchal-1.0.1.dist-info/METADATA
baghchal-1.0.1.dist-info/WHEEL
baghchal-1.0.1.dist-info/top_level.txt
baghchal-1.0.1.dist-info/RECORD
