Metadata-Version: 2.1
Name: baghchal
Version: 1.0.1
Summary: baghchal is a pure Python Bagh Chal library that supports game import, move generation, move validation and board image rendering. It also comes with a simple engine based on minimax algorithm and alpha-beta pruning.
Home-page: https://github.com/basnetsoyuj/baghchal
Author: Soyuj Jung Basnet
Author-email: bsoyuj@gmail.com
License: UNKNOWN
Download-URL: https://github.com/basnetsoyuj/baghchal/archive/v_1.0.1.tar.gz
Keywords: Bagh Chal,game environment,board game
Platform: UNKNOWN
Classifier: Programming Language :: Python :: 3
Classifier: License :: OSI Approved :: MIT License
Classifier: Operating System :: OS Independent
Requires-Dist: numpy
Requires-Dist: Pillow
